{
  "aor": 0.007011067796610169,
  "aqi": 0.014745704440677966,
  "bids_meta": {
    "RepetitionTime": 2.0,
    "SliceTiming": [
      0.0541,
      0.1081,
      0.1622,
      0.2162,
      0.2703,
      0.3243,
      0.3784,
      0.4324,
      0.4865,
      0.5405,
      0.5946,
      0.6486,
      0.7027,
      0.7568,
      0.8108,
      0.8649,
      0.9189,
      0.973,
      1.027,
      1.0811,
      1.1351,
      1.1892,
      1.2432,
      1.2973,
      1.3514,
      1.4054,
      1.4595,
      1.5135,
      1.5676,
      1.6216,
      1.6757,
      1.7297,
      1.7838,
      1.8378,
      1.8919,
      1.9459,
      2.0
    ],
    "TaskName": "rating",
    "dataset": "ds002732",
    "modality": "bold",
    "run_id": 1,
    "subject_id": "25",
    "task_id": "rating"
  },
  "dummy_trs": 0,
  "dvars_nstd": 28.020713670135827,
  "dvars_std": 1.0856225141426148,
  "dvars_vstd": 0.9645887969100172,
  "efc": 0.3978516326956305,
  "fber": 1170257.125,
  "fd_mean": 0.21265385771869694,
  "fd_num": 110,
  "fd_perc": 18.64406779661017,
  "fwhm_avg": 2.12982354978355,
  "fwhm_x": 2.1527600000000002,
  "fwhm_y": 2.430356363636364,
  "fwhm_z": 1.8063542857142856,
  "gcor": 0.0209061,
  "gsr_x": -0.015290985815227032,
  "gsr_y": 0.007630204316228628,
  "provenance": {
    "md5sum": "02e9b91796096c9392b2710cd36747f1",
    "settings": {
      "fd_thres": 0.2,
      "testing": false
    },
    "software": "mriqc",
    "version": "22.0.6",
    "webapi_port": null,
    "webapi_url": "https://mriqc.nimh.nih.gov/api/v1"
  },
  "size_t": 590,
  "size_x": 80,
  "size_y": 80,
  "size_z": 37,
  "snr": 5.208220751307131,
  "spacing_tr": 2.0,
  "spacing_x": 2.75,
  "spacing_y": 2.75,
  "spacing_z": 3.5,
  "summary_bg_k": 69.32886699530665,
  "summary_bg_mad": 0.8804179815932166,
  "summary_bg_mean": 11.901845932006836,
  "summary_bg_median": 0.6087968945503235,
  "summary_bg_n": 164635.0,
  "summary_bg_p05": 0.010780377592891455,
  "summary_bg_p95": 54.89592590332023,
  "summary_bg_stdv": 32.64181137084961,
  "summary_fg_k": 1.7228841691108574,
  "summary_fg_mad": 118.09441563379498,
  "summary_fg_mean": 681.798583984375,
  "summary_fg_median": 664.6050415039062,
  "summary_fg_n": 31084.0,
  "summary_fg_p05": 513.3337188720703,
  "summary_fg_p95": 916.4855316162108,
  "summary_fg_stdv": 127.60487365722656,
  "tsnr": 37.43352127075195
}